rebooterpro_async/__init__.py
rebooterpro_async/client.py
rebooterpro_async/data/__init__.py
rebooterpro_async/data/device_ca.pem
rebooterpro_async-0.1.0.dist-info/METADATA
rebooterpro_async-0.1.0.dist-info/WHEEL
rebooterpro_async-0.1.0.dist-info/licenses/LICENSE
rebooterpro_async-0.1.0.dist-info/RECORD
