Metadata-Version: 2.4
Name: rebooterpro-async
Version: 0.1.0
Summary: Async client for the ConnectSense Rebooter Pro local HTTPS API
Project-URL: Homepage, https://github.com/connectsense/rebooterpro-async
Project-URL: Repository, https://github.com/connectsense/rebooterpro-async
Project-URL: Issues, https://github.com/connectsense/rebooterpro-async/issues
Author-email: "Grid Connect, Inc." <support@gridconnect.com>
Maintainer-email: Jonathan Witthoeft <jonw@gridconnect.com>
License: MIT
License-File: LICENSE
Classifier: License :: OSI Approved :: MIT License
Classifier: Operating System :: OS Independent
Classifier: Programming Language :: Python :: 3
Requires-Python: >=3.10
Requires-Dist: aiohttp>=3.9
